[
  {
    "question": "Which of the following is the smallest number in the hexadecimal system?",
    "options": { "A": "0", "B": "1", "C": "A", "D": "F" },
    "correct": "A"
  },
  {
    "question": "What is the binary equivalent of the decimal number 15?",
    "options": { "A": "0111", "B": "1111", "C": "0101", "D": "0011" },
    "correct": "B"
  },
  {
    "question": "Which number system is most commonly used in everyday arithmetic?",
    "options": { "A": "Binary", "B": "Decimal", "C": "Hexadecimal", "D": "Octal" },
    "correct": "B"
  },
  {
    "question": "Radix of hexadecimal number system is",
    "options": { "A": "2", "B": "5", "C": "8", "D": "16" },
    "correct": "D"
  },
  {
    "question": "(38CB)₁₆ is an example of which number system?",
    "options": { "A": "Binary", "B": "Decimal", "C": "Hexadecimal", "D": "Octal" },
    "correct": "C"
  },
  {
    "question": "The Binary Number 1111 represents the decimal number 15.",
    "options": { "A": "True", "B": "False" },
    "correct": "A"
  },
  {
    "question": "The hexadecimal system uses 2 as its base/radix.",
    "options": { "A": "True", "B": "False" },
    "correct": "B"
  },
  {
    "question": "Octal word comes from Latin word Oct which means 8.",
    "options": { "A": "True", "B": "False" },
    "correct": "A"
  },
  {
    "question": "The Binary Number System can represent any number using digits only 0 and 1.",
    "options": { "A": "True", "B": "False" },
    "correct": "A"
  },
  {
    "question": "In the Octal Number System, the digit '9' is valid.",
    "options": { "A": "True", "B": "False" },
    "correct": "B"
  },
  {
    "question": "In the Hexadecimal System, the letter 'B' represents the Decimal value 12.",
    "options": { "A": "True", "B": "False" },
    "correct": "B"
  },
  {
    "question": "Roman Number System is an example of Positional Number System.",
    "options": { "A": "True", "B": "False" },
    "correct": "B"
  }
]
